audioviz/BeatAnalysis.py
audioviz/ChordAnalysis.py
audioviz/GeneralAnalysis.py
audioviz/Panel.py
audioviz/PitchAnalysis.py
audioviz/StructureAnalysis.py
audioviz/TimbreAnalysis.py
audioviz/__init__.py
audioviz/colabInterface.py
audioviz/utils.py
audioviz-0.3.1.dist-info/METADATA
audioviz-0.3.1.dist-info/WHEEL
audioviz-0.3.1.dist-info/top_level.txt
audioviz-0.3.1.dist-info/RECORD
